playmafia/__init__.py
playmafia/choices.py
playmafia/core.py
playmafia/filters.py
playmafia/game.py
playmafia/sandbox.py
tests/__init__.py
tests/test_choices.py
tests/test_core.py
tests/test_sandbox.py
tests/sandbox/__init__.py
tests/sandbox/plugin1.py
tests/sandbox/plugin2.py
tests/sandbox/plugin3.py
playmafia-0.0.1.dist-info/LICENSE
playmafia-0.0.1.dist-info/METADATA
playmafia-0.0.1.dist-info/WHEEL
playmafia-0.0.1.dist-info/top_level.txt
playmafia-0.0.1.dist-info/RECORD
